{
  "scraped_at": "2026-06-14T21:49:41.324818+00:00",
  "scraped_at_display": "Scraped June 14, 2026 \u00b7 5:49 PM ET",
  "date_label": "June 14, 2026",
  "games": [
    {
      "gamepk": "823368",
      "time": "12:15",
      "away": "Miami Marlins",
      "home": "Pittsburgh Pirates",
      "away_starter": "Max Meyer",
      "home_starter": "Paul Skenes",
      "park": "PNC Park",
      "park_factor": "0%",
      "park_factor_class": "neut",
      "yrfi": 43.5,
      "away_proj": 3.42,
      "home_proj": 4.01,
      "model_total": 7.43,
      "away_win_pct": 41.9,
      "home_win_pct": 58.1,
      "away_ml": 135,
      "home_ml": -156,
      "ou_line": 7.5,
      "best_bet": false
    },
    {
      "gamepk": "822722",
      "time": "1:35",
      "away": "Seattle Mariners",
      "home": "Washington Nationals",
      "away_starter": "Emerson Hancock",
      "home_starter": "PJ Poulin",
      "park": "Nationals Park",
      "park_factor": "+14%",
      "park_factor_class": "pos",
      "yrfi": 56.8,
      "away_proj": 5.32,
      "home_proj": 5.5,
      "model_total": 10.82,
      "away_win_pct": 46.0,
      "home_win_pct": 54.0,
      "away_ml": -130,
      "home_ml": 112,
      "ou_line": 10.5,
      "best_bet": false
    },
    {
      "gamepk": "824823",
      "time": "1:35",
      "away": "San Diego Padres",
      "home": "Baltimore Orioles",
      "away_starter": "Walker Buehler",
      "home_starter": "Trevor Rogers",
      "park": "Oriole Park at Camden Yards",
      "park_factor": "+16%",
      "park_factor_class": "pos",
      "yrfi": 61.9,
      "away_proj": 5.72,
      "home_proj": 6.17,
      "model_total": 11.89,
      "away_win_pct": 44.6,
      "home_win_pct": 55.4,
      "away_ml": 116,
      "home_ml": -134,
      "ou_line": 10.5,
      "best_bet": false
    },
    {
      "gamepk": "822801",
      "time": "1:37",
      "away": "New York Yankees",
      "home": "Toronto Blue Jays",
      "away_starter": "Will Warren",
      "home_starter": "Patrick Corbin",
      "park": "Rogers Centre",
      "park_factor": "-6%",
      "park_factor_class": "neg",
      "yrfi": 49.4,
      "away_proj": 4.5,
      "home_proj": 4.11,
      "model_total": 8.61,
      "away_win_pct": 53.1,
      "home_win_pct": 46.9,
      "away_ml": -130,
      "home_ml": 118,
      "ou_line": 8.5,
      "best_bet": false
    },
    {
      "gamepk": "824506",
      "time": "1:40",
      "away": "Arizona Diamondbacks",
      "home": "Cincinnati Reds",
      "away_starter": "Zac Gallen",
      "home_starter": "Andrew Abbott",
      "park": "Great American Ball Park",
      "park_factor": "+11%",
      "park_factor_class": "pos",
      "yrfi": 56.6,
      "away_proj": 5.08,
      "home_proj": 5.28,
      "model_total": 10.36,
      "away_win_pct": 47.3,
      "home_win_pct": 52.7,
      "away_ml": -111,
      "home_ml": 100,
      "ou_line": 9.5,
      "best_bet": false
    },
    {
      "gamepk": "823615",
      "time": "1:40",
      "away": "Atlanta Braves",
      "home": "New York Mets",
      "away_starter": "Bryce Elder",
      "home_starter": "Freddy Peralta",
      "park": "Citi Field",
      "park_factor": "-2%",
      "park_factor_class": "neut",
      "yrfi": 48.9,
      "away_proj": 4.29,
      "home_proj": 4.69,
      "model_total": 8.98,
      "away_win_pct": 45.0,
      "home_win_pct": 55.0,
      "away_ml": 112,
      "home_ml": -125,
      "ou_line": 8.5,
      "best_bet": false
    },
    {
      "gamepk": "823693",
      "time": "2:10",
      "away": "St. Louis Cardinals",
      "home": "Minnesota Twins",
      "away_starter": "Michael McGreevy",
      "home_starter": "Taj Bradley",
      "park": "Target Field",
      "park_factor": "+0%",
      "park_factor_class": "neut",
      "yrfi": 55.2,
      "away_proj": 4.94,
      "home_proj": 5.41,
      "model_total": 10.35,
      "away_win_pct": 43.6,
      "home_win_pct": 56.4,
      "away_ml": -103,
      "home_ml": -110,
      "ou_line": 9.5,
      "best_bet": false
    },
    {
      "gamepk": "823777",
      "time": "2:10",
      "away": "Philadelphia Phillies",
      "home": "Milwaukee Brewers",
      "away_starter": "Cristopher Sanchez",
      "home_starter": "Kyle Harrison",
      "park": "American Family Field",
      "park_factor": "-7%",
      "park_factor_class": "neg",
      "yrfi": 40.2,
      "away_proj": 3.92,
      "home_proj": 3.02,
      "model_total": 6.94,
      "away_win_pct": 57.6,
      "home_win_pct": 42.4,
      "away_ml": -130,
      "home_ml": 112,
      "ou_line": 6.5,
      "best_bet": false
    },
    {
      "gamepk": "824586",
      "time": "2:10",
      "away": "Los Angeles Dodgers",
      "home": "Chicago White Sox",
      "away_starter": "Emmet Sheehan",
      "home_starter": "Bryan Hudson",
      "park": "Rate Field",
      "park_factor": "-3%",
      "park_factor_class": "neg",
      "yrfi": 50.3,
      "away_proj": 5.39,
      "home_proj": 3.83,
      "model_total": 9.22,
      "away_win_pct": 61.8,
      "home_win_pct": 38.2,
      "away_ml": -196,
      "home_ml": 170,
      "ou_line": 9.5,
      "best_bet": false
    },
    {
      "gamepk": "824099",
      "time": "2:10",
      "away": "Houston Astros",
      "home": "Kansas City Royals",
      "away_starter": "Spencer Arrighetti",
      "home_starter": "Stephen Kolek",
      "park": "Kauffman Stadium",
      "park_factor": "-8%",
      "park_factor_class": "neg",
      "yrfi": 50.2,
      "away_proj": 4.11,
      "home_proj": 4.23,
      "model_total": 8.34,
      "away_win_pct": 46.6,
      "home_win_pct": 53.4,
      "away_ml": 100,
      "home_ml": -118,
      "ou_line": 8.5,
      "best_bet": false
    },
    {
      "gamepk": "824994",
      "time": "3:05",
      "away": "Colorado Rockies",
      "home": "Oakland Athletics",
      "away_starter": "Tomoyuki Sugano",
      "home_starter": "Jeffrey Springs",
      "park": "Las Vegas Ballpark",
      "park_factor": "+47%",
      "park_factor_class": "pos",
      "yrfi": 71.4,
      "away_proj": 6.41,
      "home_proj": 7.81,
      "model_total": 14.22,
      "away_win_pct": 36.7,
      "home_win_pct": 63.3,
      "away_ml": 166,
      "home_ml": -195,
      "ou_line": 13.5,
      "best_bet": false
    },
    {
      "gamepk": "823212",
      "time": "3:10",
      "away": "Chicago Cubs",
      "home": "San Francisco Giants",
      "away_starter": "Ryan Rolison",
      "home_starter": "Logan Webb",
      "park": "Oracle Park",
      "park_factor": "-1%",
      "park_factor_class": "neut",
      "yrfi": 49.6,
      "away_proj": 4.32,
      "home_proj": 4.82,
      "model_total": 9.14,
      "away_win_pct": 42.6,
      "home_win_pct": 57.4,
      "away_ml": 116,
      "home_ml": -134,
      "ou_line": 8.5,
      "best_bet": false
    },
    {
      "gamepk": "824021",
      "time": "4:07",
      "away": "Tampa Bay Rays",
      "home": "Los Angeles Angels",
      "away_starter": "Casey Legumina",
      "home_starter": "Grayson Rodriguez",
      "park": "Angel Stadium",
      "park_factor": "+3%",
      "park_factor_class": "pos",
      "yrfi": 49.7,
      "away_proj": 4.57,
      "home_proj": 4.4,
      "model_total": 8.97,
      "away_win_pct": 49.0,
      "home_win_pct": 51.0,
      "away_ml": -122,
      "home_ml": 110,
      "ou_line": 8.5,
      "best_bet": false
    },
    {
      "gamepk": "824751",
      "time": "7:20",
      "away": "Texas Rangers",
      "home": "Boston Red Sox",
      "away_starter": "Nathan Eovaldi",
      "home_starter": "Connelly Early",
      "park": "Fenway Park",
      "park_factor": "+14%",
      "park_factor_class": "pos",
      "yrfi": 51.7,
      "away_proj": 4.9,
      "home_proj": 4.82,
      "model_total": 9.72,
      "away_win_pct": 47.6,
      "home_win_pct": 52.4,
      "away_ml": 100,
      "home_ml": -116,
      "ou_line": 9.5,
      "best_bet": false
    }
  ],
  "best_bets": []
}